romeways_kafka_queue/__init__.py
romeways_kafka_queue/config/__init__.py
romeways_kafka_queue/config/connector/__init__.py
romeways_kafka_queue/config/connector/model.py
romeways_kafka_queue/config/queue/__init__.py
romeways_kafka_queue/config/queue/model.py
romeways_kafka_queue/infrastructure/__init__.py
romeways_kafka_queue/infrastructure/connector/__init__.py
romeways_kafka_queue/infrastructure/connector/infrastructure.py
romeways_kafka_queue-0.1.0.dist-info/LICENSE
romeways_kafka_queue-0.1.0.dist-info/METADATA
romeways_kafka_queue-0.1.0.dist-info/WHEEL
romeways_kafka_queue-0.1.0.dist-info/RECORD
