Metadata-Version: 2.1
Name: romeways_kafka_queue
Version: 0.1.0
Summary: 
Author: Marco Sievers de Almeida Ximit Gaia
Author-email: im.ximit@gmail.com
Requires-Python: >=3.11,<4.0
Classifier: Programming Language :: Python :: 3
Classifier: Programming Language :: Python :: 3.11
Classifier: Programming Language :: Python :: 3.12
Requires-Dist: aiokafka (>=0.8.1,<0.9.0)
